v2ctrydan/LICENSE
v2ctrydan/__init__.py
v2ctrydan/modbus_trydan.py
v2ctrydan-0.2.3.dist-info/METADATA
v2ctrydan-0.2.3.dist-info/WHEEL
v2ctrydan-0.2.3.dist-info/RECORD
