Metadata-Version: 2.1
Name: v2ctrydan
Version: 0.2.3
Summary: A small example package
Project-URL: GitHub, https://github.com/jesusllorens79/v2ctrydan
Project-URL: Bug Tracker, https://github.com/jesusllorens79/v2ctrydan
Author-email: Jesus Llorens <jesusllorens79@gmail.com>
Classifier: License :: OSI Approved :: MIT License
Classifier: Operating System :: OS Independent
Classifier: Programming Language :: Python :: 3
Requires-Python: >=3.7
